princeapi/__init__.py
princeapi/api.py
princeapi/errors.py
princeapi-0.0.2.dist-info/LICENSE
princeapi-0.0.2.dist-info/METADATA
princeapi-0.0.2.dist-info/WHEEL
princeapi-0.0.2.dist-info/top_level.txt
princeapi-0.0.2.dist-info/RECORD
